pdata/__init__.py
pdata/client.py
pdata/input.py
pdata/time_util.py
pdata/pb/__init__.py
pdata/pb/service_pb2.py
pdata/pb/service_pb2.pyi
pdata/pb/service_pb2_grpc.py
pypdata-0.1.2.dist-info/METADATA
pypdata-0.1.2.dist-info/WHEEL
pypdata-0.1.2.dist-info/top_level.txt
pypdata-0.1.2.dist-info/RECORD
