Metadata-Version: 2.4
Name: pypdata
Version: 0.1.2
Author-email: Lingqiao Zhao <forever.3g@hotmail.com>
Classifier: Development Status :: 3 - Alpha
Classifier: Intended Audience :: Developers
Classifier: Programming Language :: Python :: 3
Classifier: Programming Language :: Python :: 3.10
Classifier: Programming Language :: Python :: 3.11
Classifier: Programming Language :: Python :: 3.12
Requires-Python: >=3.10
Requires-Dist: pandas
Requires-Dist: protobuf~=5.29.4
Requires-Dist: grpcio>=1.72.0
Requires-Dist: pyarrow>=19.0.0
